{
  "dist/curi-router.es.js": {
    "bundled": 17837,
    "minified": 6146,
    "gzipped": 2436,
    "treeshaked": {
      "rollup": {
        "code": 23,
        "import_statements": 23
      },
      "webpack": {
        "code": 1007
      }
    }
  },
  "dist/curi-router.js": {
    "bundled": 18072,
    "minified": 6336,
    "gzipped": 2516
  },
  "dist/curi-router.umd.js": {
    "bundled": 29579,
    "minified": 8926,
    "gzipped": 3673
  },
  "dist/curi-router.min.js": {
    "bundled": 29539,
    "minified": 8886,
    "gzipped": 3653
  }
}
